visci
