Metadata-Version: 1.0
Name: visci
Version: 0.7
Summary: visualization standard file structure for continuous integration
Home-page: http://www.github.com/vsoch/visci
Author: Vanessa Sochat
Author-email: vsochat@stanford.edu
License: LICENSE.txt
Platform: UNKNOWN
